setup.py
rp_add/__init__.py
rp_add/addd.py
rp_arith.egg-info/PKG-INFO
rp_arith.egg-info/SOURCES.txt
rp_arith.egg-info/dependency_links.txt
rp_arith.egg-info/top_level.txt
rp_sub/__init__.py
rp_sub/subb.py