Metadata-Version: 1.0
Name: rp-arith
Version: 1.1.0
Summary: Useful towel-related stuff.
Home-page: http://pypi.python.org/pypi/MyApplication_v010/
Author: name surname
Author-email: name@addr.ess
License: UNKNOWN
Platform: UNKNOWN
